{"metadata": {"dbt_schema_version": "https://schemas.getdbt.com/dbt/catalog/v1.json", "dbt_version": "1.7.10", "generated_at": "2026-07-22T13:17:42.179774Z", "invocation_id": "dfa91920-fe6e-4f81-9cc3-1fcdffc84711", "env": {}}, "nodes": {"model.data_platform_demo.dim_products": {"metadata": {"type": "BASE TABLE", "schema": "public_clean", "name": "dim_products", "database": "data_platform", "comment": null, "owner": "admin"}, "columns": {"product_id": {"type": "text", "index": 1, "name": "product_id", "comment": null}, "total_views": {"type": "bigint", "index": 2, "name": "total_views", "comment": null}, "total_purchases": {"type": "bigint", "index": 3, "name": "total_purchases", "comment": null}, "total_add_to_cart": {"type": "bigint", "index": 4, "name": "total_add_to_cart", "comment": null}, "total_interactions": {"type": "bigint", "index": 5, "name": "total_interactions", "comment": null}, "conversion_rate_pct": {"type": "numeric", "index": 6, "name": "conversion_rate_pct", "comment": null}}, "stats": {"has_stats": {"id": "has_stats", "label": "Has Stats?", "value": false, "include": false, "description": "Indicates whether there are statistics for this table"}}, "unique_id": "model.data_platform_demo.dim_products"}, "model.data_platform_demo.dim_users": {"metadata": {"type": "BASE TABLE", "schema": "public_clean", "name": "dim_users", "database": "data_platform", "comment": null, "owner": "admin"}, "columns": {"user_id": {"type": "text", "index": 1, "name": "user_id", "comment": null}, "first_seen_at": {"type": "date", "index": 2, "name": "first_seen_at", "comment": null}, "last_seen_at": {"type": "date", "index": 3, "name": "last_seen_at", "comment": null}, "total_events": {"type": "bigint", "index": 4, "name": "total_events", "comment": null}, "user_segment": {"type": "text", "index": 5, "name": "user_segment", "comment": null}}, "stats": {"has_stats": {"id": "has_stats", "label": "Has Stats?", "value": false, "include": false, "description": "Indicates whether there are statistics for this table"}}, "unique_id": "model.data_platform_demo.dim_users"}, "model.data_platform_demo.fct_user_events_daily": {"metadata": {"type": "BASE TABLE", "schema": "public_clean", "name": "fct_user_events_daily", "database": "data_platform", "comment": null, "owner": "admin"}, "columns": {"event_date": {"type": "date", "index": 1, "name": "event_date", "comment": null}, "event_type": {"type": "text", "index": 2, "name": "event_type", "comment": null}, "total_events": {"type": "bigint", "index": 3, "name": "total_events", "comment": null}, "unique_users": {"type": "bigint", "index": 4, "name": "unique_users", "comment": null}, "avg_duration_ms": {"type": "numeric", "index": 5, "name": "avg_duration_ms", "comment": null}, "total_duration_seconds": {"type": "numeric", "index": 6, "name": "total_duration_seconds", "comment": null}}, "stats": {"has_stats": {"id": "has_stats", "label": "Has Stats?", "value": false, "include": false, "description": "Indicates whether there are statistics for this table"}}, "unique_id": "model.data_platform_demo.fct_user_events_daily"}, "model.data_platform_demo.stg_user_events": {"metadata": {"type": "VIEW", "schema": "public_raw", "name": "stg_user_events", "database": "data_platform", "comment": null, "owner": "admin"}, "columns": {"event_id": {"type": "text", "index": 1, "name": "event_id", "comment": null}, "user_id": {"type": "text", "index": 2, "name": "user_id", "comment": null}, "event_type": {"type": "text", "index": 3, "name": "event_type", "comment": null}, "product_id": {"type": "text", "index": 4, "name": "product_id", "comment": null}, "event_ts": {"type": "timestamp with time zone", "index": 5, "name": "event_ts", "comment": null}, "event_date": {"type": "date", "index": 6, "name": "event_date", "comment": null}, "page": {"type": "text", "index": 7, "name": "page", "comment": null}, "referrer": {"type": "text", "index": 8, "name": "referrer", "comment": null}, "duration_ms": {"type": "bigint", "index": 9, "name": "duration_ms", "comment": null}, "device": {"type": "text", "index": 10, "name": "device", "comment": null}, "browser": {"type": "text", "index": 11, "name": "browser", "comment": null}, "processed_at": {"type": "timestamp without time zone", "index": 12, "name": "processed_at", "comment": null}, "processing_date": {"type": "date", "index": 13, "name": "processing_date", "comment": null}}, "stats": {"has_stats": {"id": "has_stats", "label": "Has Stats?", "value": false, "include": false, "description": "Indicates whether there are statistics for this table"}}, "unique_id": "model.data_platform_demo.stg_user_events"}, "test.data_platform_demo.not_null_dim_products_product_id.c8aba288d1": {"metadata": {"type": "BASE TABLE", "schema": "public_test_failures", "name": "not_null_dim_products_product_id", "database": "data_platform", "comment": null, "owner": "admin"}, "columns": {"product_id": {"type": "text", "index": 1, "name": "product_id", "comment": null}, "total_views": {"type": "bigint", "index": 2, "name": "total_views", "comment": null}, "total_purchases": {"type": "bigint", "index": 3, "name": "total_purchases", "comment": null}, "total_add_to_cart": {"type": "bigint", "index": 4, "name": "total_add_to_cart", "comment": null}, "total_interactions": {"type": "bigint", "index": 5, "name": "total_interactions", "comment": null}, "conversion_rate_pct": {"type": "numeric", "index": 6, "name": "conversion_rate_pct", "comment": null}}, "stats": {"has_stats": {"id": "has_stats", "label": "Has Stats?", "value": false, "include": false, "description": "Indicates whether there are statistics for this table"}}, "unique_id": "test.data_platform_demo.not_null_dim_products_product_id.c8aba288d1"}, "test.data_platform_demo.not_null_dim_users_user_id.e754bb5812": {"metadata": {"type": "BASE TABLE", "schema": "public_test_failures", "name": "not_null_dim_users_user_id", "database": "data_platform", "comment": null, "owner": "admin"}, "columns": {"user_id": {"type": "text", "index": 1, "name": "user_id", "comment": null}, "first_seen_at": {"type": "date", "index": 2, "name": "first_seen_at", "comment": null}, "last_seen_at": {"type": "date", "index": 3, "name": "last_seen_at", "comment": null}, "total_events": {"type": "bigint", "index": 4, "name": "total_events", "comment": null}, "user_segment": {"type": "text", "index": 5, "name": "user_segment", "comment": null}}, "stats": {"has_stats": {"id": "has_stats", "label": "Has Stats?", "value": false, "include": false, "description": "Indicates whether there are statistics for this table"}}, "unique_id": "test.data_platform_demo.not_null_dim_users_user_id.e754bb5812"}, "test.data_platform_demo.not_null_fct_user_events_daily_event_date.1a0d89eb16": {"metadata": {"type": "BASE TABLE", "schema": "public_test_failures", "name": "not_null_fct_user_events_daily_event_date", "database": "data_platform", "comment": null, "owner": "admin"}, "columns": {"event_date": {"type": "date", "index": 1, "name": "event_date", "comment": null}, "event_type": {"type": "text", "index": 2, "name": "event_type", "comment": null}, "total_events": {"type": "bigint", "index": 3, "name": "total_events", "comment": null}, "unique_users": {"type": "bigint", "index": 4, "name": "unique_users", "comment": null}, "avg_duration_ms": {"type": "numeric", "index": 5, "name": "avg_duration_ms", "comment": null}, "total_duration_seconds": {"type": "numeric", "index": 6, "name": "total_duration_seconds", "comment": null}}, "stats": {"has_stats": {"id": "has_stats", "label": "Has Stats?", "value": false, "include": false, "description": "Indicates whether there are statistics for this table"}}, "unique_id": "test.data_platform_demo.not_null_fct_user_events_daily_event_date.1a0d89eb16"}, "test.data_platform_demo.not_null_fct_user_events_daily_event_type.231e1dfcd8": {"metadata": {"type": "BASE TABLE", "schema": "public_test_failures", "name": "not_null_fct_user_events_daily_event_type", "database": "data_platform", "comment": null, "owner": "admin"}, "columns": {"event_date": {"type": "date", "index": 1, "name": "event_date", "comment": null}, "event_type": {"type": "text", "index": 2, "name": "event_type", "comment": null}, "total_events": {"type": "bigint", "index": 3, "name": "total_events", "comment": null}, "unique_users": {"type": "bigint", "index": 4, "name": "unique_users", "comment": null}, "avg_duration_ms": {"type": "numeric", "index": 5, "name": "avg_duration_ms", "comment": null}, "total_duration_seconds": {"type": "numeric", "index": 6, "name": "total_duration_seconds", "comment": null}}, "stats": {"has_stats": {"id": "has_stats", "label": "Has Stats?", "value": false, "include": false, "description": "Indicates whether there are statistics for this table"}}, "unique_id": "test.data_platform_demo.not_null_fct_user_events_daily_event_type.231e1dfcd8"}, "test.data_platform_demo.not_null_stg_user_events_event_id.3ab7415ad7": {"metadata": {"type": "BASE TABLE", "schema": "public_test_failures", "name": "not_null_stg_user_events_event_id", "database": "data_platform", "comment": null, "owner": "admin"}, "columns": {"event_id": {"type": "text", "index": 1, "name": "event_id", "comment": null}, "user_id": {"type": "text", "index": 2, "name": "user_id", "comment": null}, "event_type": {"type": "text", "index": 3, "name": "event_type", "comment": null}, "product_id": {"type": "text", "index": 4, "name": "product_id", "comment": null}, "event_ts": {"type": "timestamp with time zone", "index": 5, "name": "event_ts", "comment": null}, "event_date": {"type": "date", "index": 6, "name": "event_date", "comment": null}, "page": {"type": "text", "index": 7, "name": "page", "comment": null}, "referrer": {"type": "text", "index": 8, "name": "referrer", "comment": null}, "duration_ms": {"type": "bigint", "index": 9, "name": "duration_ms", "comment": null}, "device": {"type": "text", "index": 10, "name": "device", "comment": null}, "browser": {"type": "text", "index": 11, "name": "browser", "comment": null}, "processed_at": {"type": "timestamp without time zone", "index": 12, "name": "processed_at", "comment": null}, "processing_date": {"type": "date", "index": 13, "name": "processing_date", "comment": null}}, "stats": {"has_stats": {"id": "has_stats", "label": "Has Stats?", "value": false, "include": false, "description": "Indicates whether there are statistics for this table"}}, "unique_id": "test.data_platform_demo.not_null_stg_user_events_event_id.3ab7415ad7"}, "test.data_platform_demo.not_null_stg_user_events_event_type.f7ff2a1612": {"metadata": {"type": "BASE TABLE", "schema": "public_test_failures", "name": "not_null_stg_user_events_event_type", "database": "data_platform", "comment": null, "owner": "admin"}, "columns": {"event_id": {"type": "text", "index": 1, "name": "event_id", "comment": null}, "user_id": {"type": "text", "index": 2, "name": "user_id", "comment": null}, "event_type": {"type": "text", "index": 3, "name": "event_type", "comment": null}, "product_id": {"type": "text", "index": 4, "name": "product_id", "comment": null}, "event_ts": {"type": "timestamp with time zone", "index": 5, "name": "event_ts", "comment": null}, "event_date": {"type": "date", "index": 6, "name": "event_date", "comment": null}, "page": {"type": "text", "index": 7, "name": "page", "comment": null}, "referrer": {"type": "text", "index": 8, "name": "referrer", "comment": null}, "duration_ms": {"type": "bigint", "index": 9, "name": "duration_ms", "comment": null}, "device": {"type": "text", "index": 10, "name": "device", "comment": null}, "browser": {"type": "text", "index": 11, "name": "browser", "comment": null}, "processed_at": {"type": "timestamp without time zone", "index": 12, "name": "processed_at", "comment": null}, "processing_date": {"type": "date", "index": 13, "name": "processing_date", "comment": null}}, "stats": {"has_stats": {"id": "has_stats", "label": "Has Stats?", "value": false, "include": false, "description": "Indicates whether there are statistics for this table"}}, "unique_id": "test.data_platform_demo.not_null_stg_user_events_event_type.f7ff2a1612"}, "test.data_platform_demo.not_null_stg_user_events_user_id.82058db005": {"metadata": {"type": "BASE TABLE", "schema": "public_test_failures", "name": "not_null_stg_user_events_user_id", "database": "data_platform", "comment": null, "owner": "admin"}, "columns": {"event_id": {"type": "text", "index": 1, "name": "event_id", "comment": null}, "user_id": {"type": "text", "index": 2, "name": "user_id", "comment": null}, "event_type": {"type": "text", "index": 3, "name": "event_type", "comment": null}, "product_id": {"type": "text", "index": 4, "name": "product_id", "comment": null}, "event_ts": {"type": "timestamp with time zone", "index": 5, "name": "event_ts", "comment": null}, "event_date": {"type": "date", "index": 6, "name": "event_date", "comment": null}, "page": {"type": "text", "index": 7, "name": "page", "comment": null}, "referrer": {"type": "text", "index": 8, "name": "referrer", "comment": null}, "duration_ms": {"type": "bigint", "index": 9, "name": "duration_ms", "comment": null}, "device": {"type": "text", "index": 10, "name": "device", "comment": null}, "browser": {"type": "text", "index": 11, "name": "browser", "comment": null}, "processed_at": {"type": "timestamp without time zone", "index": 12, "name": "processed_at", "comment": null}, "processing_date": {"type": "date", "index": 13, "name": "processing_date", "comment": null}}, "stats": {"has_stats": {"id": "has_stats", "label": "Has Stats?", "value": false, "include": false, "description": "Indicates whether there are statistics for this table"}}, "unique_id": "test.data_platform_demo.not_null_stg_user_events_user_id.82058db005"}, "test.data_platform_demo.source_accepted_values_raw_data_user_events_event_type__click__view__add_to_cart__purchase__search__logout.cc940b90cb": {"metadata": {"type": "BASE TABLE", "schema": "public_test_failures", "name": "source_accepted_values_raw_dat_71d88b78ccec556e423984c453534857", "database": "data_platform", "comment": null, "owner": "admin"}, "columns": {"value_field": {"type": "text", "index": 1, "name": "value_field", "comment": null}, "n_records": {"type": "bigint", "index": 2, "name": "n_records", "comment": null}}, "stats": {"has_stats": {"id": "has_stats", "label": "Has Stats?", "value": false, "include": false, "description": "Indicates whether there are statistics for this table"}}, "unique_id": "test.data_platform_demo.source_accepted_values_raw_data_user_events_event_type__click__view__add_to_cart__purchase__search__logout.cc940b90cb"}, "test.data_platform_demo.source_not_null_raw_data_user_events_event_id.5326fdaea5": {"metadata": {"type": "BASE TABLE", "schema": "public_test_failures", "name": "source_not_null_raw_data_user_events_event_id", "database": "data_platform", "comment": null, "owner": "admin"}, "columns": {"event_id": {"type": "text", "index": 1, "name": "event_id", "comment": null}, "user_id": {"type": "text", "index": 2, "name": "user_id", "comment": null}, "event_type": {"type": "text", "index": 3, "name": "event_type", "comment": null}, "product_id": {"type": "text", "index": 4, "name": "product_id", "comment": null}, "timestamp": {"type": "timestamp with time zone", "index": 5, "name": "timestamp", "comment": null}, "page": {"type": "text", "index": 6, "name": "page", "comment": null}, "referrer": {"type": "text", "index": 7, "name": "referrer", "comment": null}, "duration_ms": {"type": "bigint", "index": 8, "name": "duration_ms", "comment": null}, "device": {"type": "text", "index": 9, "name": "device", "comment": null}, "browser": {"type": "text", "index": 10, "name": "browser", "comment": null}, "event_ts": {"type": "timestamp with time zone", "index": 11, "name": "event_ts", "comment": null}, "processed_at": {"type": "timestamp without time zone", "index": 12, "name": "processed_at", "comment": null}, "processing_date": {"type": "date", "index": 13, "name": "processing_date", "comment": null}}, "stats": {"has_stats": {"id": "has_stats", "label": "Has Stats?", "value": false, "include": false, "description": "Indicates whether there are statistics for this table"}}, "unique_id": "test.data_platform_demo.source_not_null_raw_data_user_events_event_id.5326fdaea5"}, "test.data_platform_demo.source_not_null_raw_data_user_events_event_type.b7002126da": {"metadata": {"type": "BASE TABLE", "schema": "public_test_failures", "name": "source_not_null_raw_data_user_events_event_type", "database": "data_platform", "comment": null, "owner": "admin"}, "columns": {"event_id": {"type": "text", "index": 1, "name": "event_id", "comment": null}, "user_id": {"type": "text", "index": 2, "name": "user_id", "comment": null}, "event_type": {"type": "text", "index": 3, "name": "event_type", "comment": null}, "product_id": {"type": "text", "index": 4, "name": "product_id", "comment": null}, "timestamp": {"type": "timestamp with time zone", "index": 5, "name": "timestamp", "comment": null}, "page": {"type": "text", "index": 6, "name": "page", "comment": null}, "referrer": {"type": "text", "index": 7, "name": "referrer", "comment": null}, "duration_ms": {"type": "bigint", "index": 8, "name": "duration_ms", "comment": null}, "device": {"type": "text", "index": 9, "name": "device", "comment": null}, "browser": {"type": "text", "index": 10, "name": "browser", "comment": null}, "event_ts": {"type": "timestamp with time zone", "index": 11, "name": "event_ts", "comment": null}, "processed_at": {"type": "timestamp without time zone", "index": 12, "name": "processed_at", "comment": null}, "processing_date": {"type": "date", "index": 13, "name": "processing_date", "comment": null}}, "stats": {"has_stats": {"id": "has_stats", "label": "Has Stats?", "value": false, "include": false, "description": "Indicates whether there are statistics for this table"}}, "unique_id": "test.data_platform_demo.source_not_null_raw_data_user_events_event_type.b7002126da"}, "test.data_platform_demo.source_not_null_raw_data_user_events_user_id.00a4e601fb": {"metadata": {"type": "BASE TABLE", "schema": "public_test_failures", "name": "source_not_null_raw_data_user_events_user_id", "database": "data_platform", "comment": null, "owner": "admin"}, "columns": {"event_id": {"type": "text", "index": 1, "name": "event_id", "comment": null}, "user_id": {"type": "text", "index": 2, "name": "user_id", "comment": null}, "event_type": {"type": "text", "index": 3, "name": "event_type", "comment": null}, "product_id": {"type": "text", "index": 4, "name": "product_id", "comment": null}, "timestamp": {"type": "timestamp with time zone", "index": 5, "name": "timestamp", "comment": null}, "page": {"type": "text", "index": 6, "name": "page", "comment": null}, "referrer": {"type": "text", "index": 7, "name": "referrer", "comment": null}, "duration_ms": {"type": "bigint", "index": 8, "name": "duration_ms", "comment": null}, "device": {"type": "text", "index": 9, "name": "device", "comment": null}, "browser": {"type": "text", "index": 10, "name": "browser", "comment": null}, "event_ts": {"type": "timestamp with time zone", "index": 11, "name": "event_ts", "comment": null}, "processed_at": {"type": "timestamp without time zone", "index": 12, "name": "processed_at", "comment": null}, "processing_date": {"type": "date", "index": 13, "name": "processing_date", "comment": null}}, "stats": {"has_stats": {"id": "has_stats", "label": "Has Stats?", "value": false, "include": false, "description": "Indicates whether there are statistics for this table"}}, "unique_id": "test.data_platform_demo.source_not_null_raw_data_user_events_user_id.00a4e601fb"}, "test.data_platform_demo.source_unique_raw_data_user_events_event_id.ea36ee7001": {"metadata": {"type": "BASE TABLE", "schema": "public_test_failures", "name": "source_unique_raw_data_user_events_event_id", "database": "data_platform", "comment": null, "owner": "admin"}, "columns": {"unique_field": {"type": "text", "index": 1, "name": "unique_field", "comment": null}, "n_records": {"type": "bigint", "index": 2, "name": "n_records", "comment": null}}, "stats": {"has_stats": {"id": "has_stats", "label": "Has Stats?", "value": false, "include": false, "description": "Indicates whether there are statistics for this table"}}, "unique_id": "test.data_platform_demo.source_unique_raw_data_user_events_event_id.ea36ee7001"}, "test.data_platform_demo.unique_dim_products_product_id.ef7b2a9985": {"metadata": {"type": "BASE TABLE", "schema": "public_test_failures", "name": "unique_dim_products_product_id", "database": "data_platform", "comment": null, "owner": "admin"}, "columns": {"unique_field": {"type": "text", "index": 1, "name": "unique_field", "comment": null}, "n_records": {"type": "bigint", "index": 2, "name": "n_records", "comment": null}}, "stats": {"has_stats": {"id": "has_stats", "label": "Has Stats?", "value": false, "include": false, "description": "Indicates whether there are statistics for this table"}}, "unique_id": "test.data_platform_demo.unique_dim_products_product_id.ef7b2a9985"}, "test.data_platform_demo.unique_dim_users_user_id.bcdc17b9f9": {"metadata": {"type": "BASE TABLE", "schema": "public_test_failures", "name": "unique_dim_users_user_id", "database": "data_platform", "comment": null, "owner": "admin"}, "columns": {"unique_field": {"type": "text", "index": 1, "name": "unique_field", "comment": null}, "n_records": {"type": "bigint", "index": 2, "name": "n_records", "comment": null}}, "stats": {"has_stats": {"id": "has_stats", "label": "Has Stats?", "value": false, "include": false, "description": "Indicates whether there are statistics for this table"}}, "unique_id": "test.data_platform_demo.unique_dim_users_user_id.bcdc17b9f9"}, "test.data_platform_demo.unique_stg_user_events_event_id.6926ae65d7": {"metadata": {"type": "BASE TABLE", "schema": "public_test_failures", "name": "unique_stg_user_events_event_id", "database": "data_platform", "comment": null, "owner": "admin"}, "columns": {"unique_field": {"type": "text", "index": 1, "name": "unique_field", "comment": null}, "n_records": {"type": "bigint", "index": 2, "name": "n_records", "comment": null}}, "stats": {"has_stats": {"id": "has_stats", "label": "Has Stats?", "value": false, "include": false, "description": "Indicates whether there are statistics for this table"}}, "unique_id": "test.data_platform_demo.unique_stg_user_events_event_id.6926ae65d7"}}, "sources": {"source.data_platform_demo.raw_data.user_events": {"metadata": {"type": "BASE TABLE", "schema": "raw", "name": "user_events", "database": "data_platform", "comment": null, "owner": "admin"}, "columns": {"event_id": {"type": "text", "index": 1, "name": "event_id", "comment": null}, "user_id": {"type": "text", "index": 2, "name": "user_id", "comment": null}, "event_type": {"type": "text", "index": 3, "name": "event_type", "comment": null}, "product_id": {"type": "text", "index": 4, "name": "product_id", "comment": null}, "timestamp": {"type": "timestamp with time zone", "index": 5, "name": "timestamp", "comment": null}, "page": {"type": "text", "index": 6, "name": "page", "comment": null}, "referrer": {"type": "text", "index": 7, "name": "referrer", "comment": null}, "duration_ms": {"type": "bigint", "index": 8, "name": "duration_ms", "comment": null}, "device": {"type": "text", "index": 9, "name": "device", "comment": null}, "browser": {"type": "text", "index": 10, "name": "browser", "comment": null}, "event_ts": {"type": "timestamp with time zone", "index": 11, "name": "event_ts", "comment": null}, "processed_at": {"type": "timestamp without time zone", "index": 12, "name": "processed_at", "comment": null}, "processing_date": {"type": "date", "index": 13, "name": "processing_date", "comment": null}}, "stats": {"has_stats": {"id": "has_stats", "label": "Has Stats?", "value": false, "include": false, "description": "Indicates whether there are statistics for this table"}}, "unique_id": "source.data_platform_demo.raw_data.user_events"}}, "errors": null}